grip/__init__.py
grip/grip_multiviews.py
grip/grip_pairwise.py
grip/icp.py
grip/initializers.py
grip/jrmpc.py
grip/se3.py
grip/__pycache__/DEV_icp.cpython-311.pyc
grip/__pycache__/__init__.cpython-311.pyc
grip/__pycache__/__init__.cpython-38.pyc
grip/__pycache__/__init__.cpython-39.pyc
grip/__pycache__/briff_multiviews.cpython-311.pyc
grip/__pycache__/briff_multiviews.cpython-38.pyc
grip/__pycache__/briff_multiviews.cpython-39.pyc
grip/__pycache__/briff_pairwise.cpython-311.pyc
grip/__pycache__/briff_pairwise.cpython-38.pyc
grip/__pycache__/briff_pairwise.cpython-39.pyc
grip/__pycache__/distances_utils.cpython-311.pyc
grip/__pycache__/flames.cpython-311.pyc
grip/__pycache__/flames.cpython-38.pyc
grip/__pycache__/flames_multiviews.cpython-38.pyc
grip/__pycache__/flames_pairwise.cpython-38.pyc
grip/__pycache__/icp.cpython-311.pyc
grip/__pycache__/icp.cpython-38.pyc
grip/__pycache__/icp.cpython-39.pyc
grip/__pycache__/initializers.cpython-311.pyc
grip/__pycache__/initializers.cpython-39.pyc
grip/__pycache__/jrmpc.cpython-311.pyc
grip/__pycache__/jrmpc.cpython-38.pyc
grip/__pycache__/jrmpc.cpython-39.pyc
grip/__pycache__/lms.cpython-38.pyc
grip/__pycache__/pcd_utils.cpython-311.pyc
grip/__pycache__/pcd_utils.cpython-38.pyc
grip/__pycache__/se3.cpython-311.pyc
grip/__pycache__/se3.cpython-39.pyc
grip/__pycache__/se3_BACKUP.cpython-311.pyc
grip/__pycache__/se3_geodesic_distance.cpython-311.pyc
grip/__pycache__/se3_geodesic_distances.cpython-311.pyc
grip/__pycache__/so3.cpython-311.pyc
grip/__pycache__/so3.cpython-38.pyc
grip/utils/__init__.py
grip/utils/chamfer.py
grip/utils/chamfer_newer_pytorch3d.py
grip/utils/misc.py
grip/utils/pcd.py
grip/utils/types.py
grip/utils/__pycache__/__init__.cpython-311.pyc
grip/utils/__pycache__/__init__.cpython-39.pyc
grip/utils/__pycache__/chamfer.cpython-311.pyc
grip/utils/__pycache__/chamfer.cpython-39.pyc
grip/utils/__pycache__/chamfer_newer_pytorch3d.cpython-39.pyc
grip/utils/__pycache__/flames.cpython-311.pyc
gripcd-0.1.2.dist-info/METADATA
gripcd-0.1.2.dist-info/WHEEL
gripcd-0.1.2.dist-info/top_level.txt
gripcd-0.1.2.dist-info/RECORD
